ShynaTaskManager/__init__.py
ShynaTaskManager/shyna_alarm.py
ShynaTaskManager/shyna_perform_task.py
ShynaTaskManager-0.0.11.dist-info/LICENSE
ShynaTaskManager-0.0.11.dist-info/METADATA
ShynaTaskManager-0.0.11.dist-info/WHEEL
ShynaTaskManager-0.0.11.dist-info/top_level.txt
ShynaTaskManager-0.0.11.dist-info/RECORD
