Metadata-Version: 2.1
Name: ShynaTaskManager
Version: 0.0.11
Summary: Shyna Task Manager, Phase one
Author: Shivam Sharma
Author-email: shivamsharma1913@gmail.com
License-File: LICENSE
Requires-Dist: setuptools
Requires-Dist: wheel
Requires-Dist: ShynaDatabase
Requires-Dist: ShynaTime
